metamancer-0.0.4a0.dist-info/METADATA
metamancer-0.0.4a0.dist-info/WHEEL
metamancer-0.0.4a0.dist-info/entry_points.txt
metamancer/__init__.py
metamancer/apparatus.py
metamancer/exif_base.py
metamancer/iptc.py
metamancer/metadata.py
metamancer/scholia.py
metamancer/xmp.py
metamancer-0.0.4a0.dist-info/RECORD
