Metadata-Version: 2.1
Name: MetaMancer
Version: 0.0.4a0
Summary: Manipulate File metadata like a wizard-engineer!
Keywords: metadata,reader,writer,parser,extract,edit,exif,iptc,xmp,file,photo,image,jpeg,jpg,png,tiff,raw,location,gps,geotag,camera,date,time,title,comment,label,tag
Author-Email: Cody M Sommer <bassmastacod@gmail.com>
License: MIT
Classifier: License :: OSI Approved :: MIT License
Classifier: Programming Language :: Python :: 3.8
Classifier: Programming Language :: Python :: 3.9
Classifier: Programming Language :: Python :: 3.10
Classifier: Programming Language :: Python :: 3.11
Classifier: Programming Language :: Python :: 3.12
Classifier: Programming Language :: Python :: 3.13
Classifier: Programming Language :: Python :: 3.14
Classifier: Development Status :: 3 - Alpha
Classifier: Intended Audience :: Developers
Classifier: Topic :: Software Development :: Libraries
Classifier: Typing :: Typed
Project-URL: Repository, https://github.com/BassMastaCod/MetaMancer.git
Project-URL: Issues, https://github.com/BassMastaCod/MetaMancer/issues
Requires-Python: >=3.8
Requires-Dist: folium
Requires-Dist: networkx
Requires-Dist: cachetools
Requires-Dist: piexif
Requires-Dist: Pillow
Requires-Dist: iptcinfo3
